README.md
setup.py
wxy_Mail/__init__.py
wxy_Mail.egg-info/PKG-INFO
wxy_Mail.egg-info/SOURCES.txt
wxy_Mail.egg-info/dependency_links.txt
wxy_Mail.egg-info/top_level.txt