Metadata-Version: 1.0
Name: wxy-Mail
Version: 0.0.1
Summary: 发送邮件相关操作
Home-page: https://gitee.com/wang_xing_yuan/wxy-Mail.git
Author: cooper.wang
Author-email: UNKNOWN
License: MIT
Platform: UNKNOWN
